a2a/__init__.py
a2a/version.py
a2a/adapters/__init__.py
a2a/adapters/crewai.py
a2a/adapters/langgraph.py
a2a/cli/__init__.py
a2a/cli/main.py
a2a/client/__init__.py
a2a/client/agent_client.py
a2a/client/discovery.py
a2a/client/orchestrator.py
a2a/config/__init__.py
a2a/config/llm_config.py
a2a/control/__init__.py
a2a/control/api.py
a2a/control/schemas.py
a2a/control/service.py
a2a/cost/__init__.py
a2a/cost/budget.py
a2a/cost/calculator.py
a2a/cost/pricing.py
a2a/cost/tracker.py
a2a/cost/usage.py
a2a/discovery/__init__.py
a2a/discovery/base.py
a2a/discovery/registry.py
a2a/discovery/secured.py
a2a/discovery/well_known.py
a2a/enterprise/__init__.py
a2a/enterprise/audit.py
a2a/enterprise/auth_helpers.py
a2a/enterprise/hitl.py
a2a/enterprise/policy_engine.py
a2a/enterprise/rbac.py
a2a/extensions/__init__.py
a2a/extensions/activation.py
a2a/extensions/models.py
a2a/extensions/negotiation.py
a2a/extensions/validators.py
a2a/health/__init__.py
a2a/health/status.py
a2a/hitl/__init__.py
a2a/hitl/api.py
a2a/hitl/decision.py
a2a/hitl/engine.py
a2a/hitl/policy.py
a2a/hitl/request.py
a2a/hitl/store.py
a2a/llm/__init__.py
a2a/llm/base.py
a2a/llm/factory.py
a2a/llm/gemini.py
a2a/llm/groq.py
a2a/llm/ollama.py
a2a/llm/openai.py
a2a/mcp/__init__.py
a2a/mcp/adapters.py
a2a/mcp/client.py
a2a/mcp/executor.py
a2a/mcp/registry.py
a2a/mcp/schema.py
a2a/mcp/server.py
a2a/memory/__init__.py
a2a/memory/query.py
a2a/memory/record.py
a2a/memory/replay.py
a2a/memory/serializer.py
a2a/memory/store.py
a2a/observability/__init__.py
a2a/observability/logging.py
a2a/observability/tracing.py
a2a/policy/__init__.py
a2a/policy/context.py
a2a/policy/decision.py
a2a/policy/engine.py
a2a/policy/presets.py
a2a/policy/rules.py
a2a/protocol/__init__.py
a2a/protocol/conversation.py
a2a/protocol/errors.py
a2a/protocol/lifecycle.py
a2a/protocol/notifications.py
a2a/protocol/trust.py
a2a/protocol/versioning.py
a2a/resilience/__init__.py
a2a/resilience/breaker.py
a2a/resilience/fallback.py
a2a/resilience/router.py
a2a_python_sdk-0.1.6.dist-info/licenses/LICENSE
a2a_python_sdk-0.1.6.dist-info/METADATA
a2a_python_sdk-0.1.6.dist-info/WHEEL
a2a_python_sdk-0.1.6.dist-info/top_level.txt
a2a_python_sdk-0.1.6.dist-info/RECORD
