Metadata-Version: 2.4
Name: a2a-python-sdk
Version: 0.1.6
Summary: Agent-to-Agent (A2A) Protocol Python SDK
Author-email: Ganesh Kinkar Giri <k.ganeshgiri@gmail.com>
License: Apache-2.0
Keywords: a2a,agentic-ai,multi-agent,llm,langgraph,crewai,mcp,ai-agents,enterprise-ai
Classifier: Development Status :: 4 - Beta
Classifier: Intended Audience :: Developers
Classifier: Intended Audience :: Information Technology
Classifier: License :: OSI Approved :: Apache Software License
Classifier: Programming Language :: Python :: 3
Classifier: Programming Language :: Python :: 3.10
Classifier: Programming Language :: Python :: 3.11
Classifier: Programming Language :: Python :: 3.12
Classifier: Topic :: Software Development :: Libraries
Classifier: Topic :: Scientific/Engineering :: Artificial Intelligence
Requires-Python: >=3.10
License-File: LICENSE
Requires-Dist: pydantic>=2.0
Requires-Dist: requests>=2.31
Requires-Dist: httpx>=0.25
Requires-Dist: pyjwt>=2.8
Requires-Dist: typing-extensions>=4.8
Provides-Extra: server
Requires-Dist: fastapi>=0.110; extra == "server"
Requires-Dist: uvicorn[standard]>=0.29; extra == "server"
Provides-Extra: streaming
Requires-Dist: sse-starlette>=2.0; extra == "streaming"
Requires-Dist: websockets>=12.0; extra == "streaming"
Provides-Extra: security
Requires-Dist: cryptography>=42.0; extra == "security"
Requires-Dist: python-jose>=3.3; extra == "security"
Provides-Extra: observability
Requires-Dist: opentelemetry-api>=1.24; extra == "observability"
Requires-Dist: opentelemetry-sdk>=1.24; extra == "observability"
Requires-Dist: opentelemetry-exporter-otlp>=1.24; extra == "observability"
Provides-Extra: llm
Requires-Dist: openai>=1.0; extra == "llm"
Requires-Dist: groq>=0.9; extra == "llm"
Requires-Dist: ollama>=0.1; extra == "llm"
Provides-Extra: frameworks
Requires-Dist: langgraph>=0.2; extra == "frameworks"
Requires-Dist: crewai>=0.30; extra == "frameworks"
Provides-Extra: mcp
Requires-Dist: anyio>=4.0; extra == "mcp"
Provides-Extra: cli
Requires-Dist: click>=8.1; extra == "cli"
Requires-Dist: rich>=13.7; extra == "cli"
Provides-Extra: dev
Requires-Dist: watchfiles>=0.21; extra == "dev"
Requires-Dist: python-dotenv>=1.0; extra == "dev"
Provides-Extra: test
Requires-Dist: pytest>=8.0; extra == "test"
Requires-Dist: pytest-asyncio>=0.23; extra == "test"
Requires-Dist: pytest-cov>=5.0; extra == "test"
Provides-Extra: all
Requires-Dist: a2a-python[cli,dev,frameworks,llm,mcp,observability,security,server,streaming,test]; extra == "all"
Dynamic: license-file
